pretix_ldap/__init__.py
pretix_ldap/ldap_connector.py
pretix_ldap-0.2.5.dist-info/LICENSE
pretix_ldap-0.2.5.dist-info/METADATA
pretix_ldap-0.2.5.dist-info/WHEEL
pretix_ldap-0.2.5.dist-info/entry_points.txt
pretix_ldap-0.2.5.dist-info/top_level.txt
pretix_ldap-0.2.5.dist-info/RECORD
