Metadata-Version: 2.1
Name: pretix-ldap
Version: 0.2.5
Summary: LDAP authentication backend for pretix
Home-page: https://github.com/Sohalt/pretix-ldap
Author: sohalt
Author-email: sohalt@sohalt.net
License: Apache Software License
License-File: LICENSE
Requires-Dist: ldap3
